{
  "run_at": "2026-04-30T19:47:54Z",
  "mode": "retrospective 5y",
  "since": "2021-05-01",
  "new_papers": 1664,
  "total_seen": 1664,
  "digest_filename": "digest_2026-04-30.md",
  "topic_counts": {
    "zymot_microfluidic": 38,
    "sperm_dna_fragmentation": 137,
    "sperm_dna_double_strand": 46,
    "tese_high_dfi": 40,
    "antioxidant_culture_media": 56,
    "varicocele_embolisation_ivf": 58,
    "blastocyst_grading_outcomes": 108,
    "recurrent_implantation_failure": 200,
    "endometrial_receptivity_era": 200,
    "methylation_mthfr_art": 126,
    "rapamycin": 49,
    "embryo_arrest_d3_blast": 200,
    "antagonist_protocol_normoresponder": 162,
    "time_lapse_morphokinetics": 200,
    "intercycle_interval": 13,
    "haploid_embryos_decondensation": 59,
    "duostim_luteal_phase": 54,
    "picsi_hyaluronan_binding": 17,
    "pgta_advanced_age": 139,
    "agonist_vs_dual_trigger": 61,
    "choline_pemt_pregnancy": 13,
    "lead_follicle_oversize": 48,
    "growth_hormone_adjuvant": 23,
    "agonist_trigger_suboptimal": 14,
    "premature_ovulation": 25,
    "one_pn_embryos": 31,
    "imsi_high_mag_morphology": 8,
    "methylfolate_vs_folic_acid_ivf": 3,
    "ss31_elamipretide": 1
  }
}